{
  "layout": [
    {
      "components": [
        "dynamic-breadcrumbs-custom"
      ],
      "width": 12
    },
    {
      "components": [
        "search-terms-summary"
      ],
      "width": 12
    },
    {
      "components": [
        "product-listing-summary-information-custom"
      ],
      "width": 12
    },
    {
      "components": [
        "sort-results"
      ],
      "width": 12
    },
    {
      "components": [
        "faceted-navigation-desktop-custom"
      ],
      "width": 3
    },
    {
      "components": [
        "dynamic-product-list-quick-view-custom",
        "product-listing-summary-information-custom",
        "custom-show-more-products-button"
      ],
      "width": 9
    },
    {
      "components": [
        "back-to-top-link"
      ],
      "width": 12
    }
  ],
  "component": "customDynamicProductListingContainer",
  "title": "customDynamicProductListingDesktop"
}